tensorflou/1.txt
tensorflou/11.txt
tensorflou/12.txt
tensorflou/13.txt
tensorflou/14.txt
tensorflou/15.txt
tensorflou/16.txt
tensorflou/17.txt
tensorflou/18.txt
tensorflou/19.txt
tensorflou/2.txt
tensorflou/20.txt
tensorflou/3.txt
tensorflou/4.txt
tensorflou/5.txt
tensorflou/__init__.py
tensorflou-2.0.dist-info/METADATA
tensorflou-2.0.dist-info/WHEEL
tensorflou-2.0.dist-info/top_level.txt
tensorflou-2.0.dist-info/RECORD
